xloil-0.20.2.data/data/share/xloil/xlOil.dll
xloil-0.20.2.data/data/share/xloil/xlOil.ini
xloil-0.20.2.data/data/share/xloil/xlOil.xll
xloil-0.20.2.data/data/share/xloil/xlOil_Install.ps1
xloil-0.20.2.data/data/share/xloil/xlOil_NewAddin.ps1
xloil-0.20.2.data/data/share/xloil/xlOil_Python.dll
xloil-0.20.2.data/data/share/xloil/xlOil_Python39.pyd
xloil-0.20.2.data/data/share/xloil/xlOil_Remove.ps1
xloil-0.20.2.data/data/share/xloil/xlOil_SQL.dll
xloil-0.20.2.data/data/share/xloil/xlOil_Utils.dll
xloil-0.20.2.data/purelib/xloil/__init__.py
xloil-0.20.2.data/purelib/xloil/_core.py
xloil-0.20.2.data/purelib/xloil/_event_loop.py
xloil-0.20.2.data/purelib/xloil/_paths.py
xloil-0.20.2.data/purelib/xloil/_superreload.py
xloil-0.20.2.data/purelib/xloil/com.py
xloil-0.20.2.data/purelib/xloil/command_line.py
xloil-0.20.2.data/purelib/xloil/debug.py
xloil-0.20.2.data/purelib/xloil/excelfuncs.py
xloil-0.20.2.data/purelib/xloil/func_inspect.py
xloil-0.20.2.data/purelib/xloil/importer.py
xloil-0.20.2.data/purelib/xloil/jupyter.py
xloil-0.20.2.data/purelib/xloil/jupyter_kernel.py
xloil-0.20.2.data/purelib/xloil/logging.py
xloil-0.20.2.data/purelib/xloil/matplotlib.py
xloil-0.20.2.data/purelib/xloil/pandas.py
xloil-0.20.2.data/purelib/xloil/pillow.py
xloil-0.20.2.data/purelib/xloil/register.py
xloil-0.20.2.data/purelib/xloil/rtd.py
xloil-0.20.2.data/purelib/xloil/type_converters.py
xloil-0.20.2.data/purelib/xloil/xloil_ribbon.py
xloil-0.20.2.data/purelib/xloil/_pyinstaller/__init__.py
xloil-0.20.2.data/purelib/xloil/_pyinstaller/hook-xloil.py
xloil-0.20.2.data/purelib/xloil/gui/__init__.py
xloil-0.20.2.data/purelib/xloil/gui/qt_console.py
xloil-0.20.2.data/purelib/xloil/gui/qtpy.py
xloil-0.20.2.data/purelib/xloil/gui/tk_console.py
xloil-0.20.2.data/purelib/xloil/gui/tkinter.py
xloil-0.20.2.data/purelib/xloil/gui/wx.py
xloil-0.20.2.data/purelib/xloil/stubs/__init__.py
xloil-0.20.2.data/purelib/xloil/stubs/xloil_core/__init__.py
xloil-0.20.2.dist-info/LICENSE
xloil-0.20.2.dist-info/METADATA
xloil-0.20.2.dist-info/WHEEL
xloil-0.20.2.dist-info/entry_points.txt
xloil-0.20.2.dist-info/top_level.txt
xloil-0.20.2.dist-info/RECORD
