Metadata-Version: 2.1
Name: xloil
Version: 0.20.2
Summary: Excel interop for Python and Jupyter
Home-page: https://gitlab.com/stevecu/xloil
Author: Steven Cunnane
Author-email: replace-this-with-my-surname@gmail.com
License: Apache
Download-URL: https://gitlab.com/stevecu/xloil/-/releases/
Project-URL: Documentation, https://xloil.readthedocs.io/en/stable
Platform: UNKNOWN
Classifier: Development Status :: 4 - Beta
Classifier: Programming Language :: Python :: 3
Classifier: Programming Language :: Python :: 3.6
Classifier: Programming Language :: Python :: 3.7
Classifier: Programming Language :: Python :: 3.8
Classifier: Programming Language :: Python :: 3.9
Classifier: Programming Language :: Python :: 3.10
Classifier: Programming Language :: Python :: 3.11
Classifier: Programming Language :: Python :: 3.12
Classifier: Programming Language :: C++
Classifier: Topic :: Software Development :: Libraries :: Python Modules
Classifier: Topic :: Office/Business :: Financial :: Spreadsheet
Classifier: Topic :: Software Development :: Libraries :: Application Frameworks
Classifier: Framework :: Jupyter
Classifier: Operating System :: Microsoft :: Windows
Requires-Python: >=3.6
License-File: LICENSE
Requires-Dist: numpy >=1.18
Requires-Dist: tomlkit
